CHANGES.txt
LICENSE.txt
README.txt
setup.cfg
setup.py
zgeo.atom-configure.zcml
zgeo/__init__.py
zgeo.atom.egg-info/PKG-INFO
zgeo.atom.egg-info/SOURCES.txt
zgeo.atom.egg-info/dependency_links.txt
zgeo.atom.egg-info/entry_points.txt
zgeo.atom.egg-info/namespace_packages.txt
zgeo.atom.egg-info/not-zip-safe
zgeo.atom.egg-info/requires.txt
zgeo.atom.egg-info/top_level.txt
zgeo/atom/README.txt
zgeo/atom/__init__.py
zgeo/atom/atom-docs.txt
zgeo/atom/atom-pub.txt
zgeo/atom/browser.py
zgeo/atom/configure.zcml
zgeo/atom/entry.pt
zgeo/atom/example.py
zgeo/atom/feedparser.py
zgeo/atom/ftesting.zcml
zgeo/atom/interfaces.py
zgeo/atom/link.py
zgeo/atom/metadata.py
zgeo/atom/publication.py
zgeo/atom/search_feed.pt
zgeo/atom/subscription_feed.pt
zgeo/atom/testing.py
zgeo/atom/tests.py
zgeo/atom/zope2.py
