Metadata-Version: 1.0
Name: zgeo.atom
Version: 0.4
Summary: Atom syndication and AtomPub with GeoRSS
Home-page: http://trac.gispython.org/projects/PrimaGIS/wiki/zgeo.atom
Author: Sean Gillies
Author-email: sgillies@frii.com
License: BSD
Keywords: gis geography geospatial georss atom atompub
Platform: UNKNOWN
Classifier: Framework :: Zope3
Classifier: Programming Language :: Python
Classifier: Topic :: Software Development :: Libraries :: Python Modules
Classifier: Topic :: Scientific/Engineering :: GIS
Classifier: Development Status :: 3 - Alpha
Classifier: Intended Audience :: Developers
Classifier: License :: OSI Approved :: BSD License
